htd/htd.v
module htd #(
  parameter DATA_WIDTH = 8
) (
    input wire                  i_clk,
    input wire                  i_rst_n,
    input wire [DATA_WIDTH-1:0] iv_data,
    input wire                  i_data_wr,
    output wire [DATA_WIDTH:0]  ov_data,
    output wire                 o_data_wr
);

  reg [DATA_WIDTH-1:0]  iv_data_reg;
  reg                   i_data_wr_reg;
  reg [DATA_WIDTH:0]    ov_data_reg;
  reg                   o_data_wr_reg;

  parameter IDLE_S = 2'b00;
  parameter TRANS_FIRST_S = 2'b01;
  parameter TRANS_S = 2'b10;
  reg [1:0] st_current;

  always @(posedge i_clk or negedge i_rst_n) begin
    if (!i_rst_n) begin
      iv_data_reg <= 0;
      i_data_wr_reg <= 0;
      ov_data_reg <= 0;
      o_data_wr_reg <= 0;
      st_current <= IDLE_S;
    end else begin
      iv_data_reg <= iv_data;
      i_data_wr_reg <= i_data_wr;
      o_data_wr_reg <= i_data_wr_reg;
    end
  end

  always @(posedge i_clk or negedge i_rst_n) begin
    case (st_current)
        IDLE_S: begin
            if (i_data_wr && !i_data_wr_reg) begin
                st_current <= TRANS_FIRST_S;
            end else
                st_current <= IDLE_S;
        end
        TRANS_FIRST_S: begin
            if (i_data_wr_reg && !o_data_wr_reg) begin
                ov_data_reg <= {1'b1, iv_data_reg};
            end else if(!i_data_wr && i_data_wr_reg) begin
                ov_data_reg <= {1'b1, iv_data_reg};
                st_current <= TRANS_S;
            end else begin
                ov_data_reg <= {1'b0, iv_data_reg};
            end
        end
        TRANS_S: begin
            st_current <= IDLE_S;
        end
    endcase
  end


  assign ov_data = ov_data_reg;
  assign o_data_wr = o_data_wr_reg;

endmodule

htd/tb_htd.v
`timescale 1ns/1ps

module tb_htd();
    // Parameters
    parameter DATA_WIDTH = 8;
    parameter CLK_PERIOD = 10;

    // Signals
    reg                   i_clk;
    reg                   i_rst_n;
    reg  [DATA_WIDTH-1:0] iv_data;
    reg                   i_data_wr;
    wire [DATA_WIDTH:0]   ov_data;
    wire                  o_data_wr;

    // Clock generation
    initial begin
        i_clk = 1'b1;
        forever #(CLK_PERIOD/2) i_clk = ~i_clk;
    end

    // DUT instantiation
    htd #(
        .DATA_WIDTH(DATA_WIDTH)
    ) htd_inst (
        .i_clk     (i_clk),
        .i_rst_n   (i_rst_n),
        .iv_data   (iv_data),
        .i_data_wr (i_data_wr),
        .ov_data   (ov_data),
        .o_data_wr (o_data_wr)
    );

    // Test stimulus
    initial begin
        // Initialize
        i_rst_n   <= 1'b0;
        iv_data   <= 8'h00;
        i_data_wr <= 1'b0;

        // Wait 100ns for global reset
        #10; i_rst_n <= 1'b1;
        #20;

        // Test cases: Send numbers 1 to 16
        repeat(6) begin
            iv_data   <= iv_data + 8'h01;  // 从1递增到16
            i_data_wr <= 1'b1;
            #10;
        end

        i_data_wr <= 1'b0;
        #10;

        repeat(6) begin
            iv_data   <= iv_data + 8'h01;  // 从1递增到16
            i_data_wr <= 1'b1;
            #10;
        end

        i_data_wr <= 1'b0;
        // End simulation
        #100;
        $finish;
    end

    // Monitor changes
    initial begin
        $monitor("Time=%0t rst_n=%0b data_wr=%0b iv_data=%0h ov_data=%0h o_data_wr=%0b",
                 $time, i_rst_n, i_data_wr, iv_data, ov_data, o_data_wr);
    end

    initial begin            
        $dumpfile("htd.vcd");        //生成的vcd文件名称
        $dumpvars(0, tb_htd);    //tb模块名称
    end

endmodule

htd/htd.vcd
$date
	Fri Jan 10 11:41:05 2025
$end
$version
	Icarus Verilog
$end
$timescale
	1ps
$end
$scope module tb_htd $end
$var wire 9 ! ov_data [8:0] $end
$var wire 1 " o_data_wr $end
$var parameter 32 # CLK_PERIOD $end
$var parameter 32 $ DATA_WIDTH $end
$var reg 1 % i_clk $end
$var reg 1 & i_data_wr $end
$var reg 1 ' i_rst_n $end
$var reg 8 ( iv_data [7:0] $end
$scope module htd_inst $end
$var wire 1 % i_clk $end
$var wire 1 & i_data_wr $end
$var wire 1 ' i_rst_n $end
$var wire 8 ) iv_data [7:0] $end
$var wire 1 " o_data_wr $end
$var wire 9 * ov_data [8:0] $end
$var parameter 32 + DATA_WIDTH $end
$var parameter 2 , IDLE_S $end
$var parameter 2 - TRANS_FIRST_S $end
$var parameter 2 . TRANS_S $end
$var reg 1 / i_data_wr_reg $end
$var reg 8 0 iv_data_reg [7:0] $end
$var reg 1 1 o_data_wr_reg $end
$var reg 9 2 ov_data_reg [8:0] $end
$var reg 2 3 st_current [1:0] $end
$upscope $end
$upscope $end
$enddefinitions $end
$comment Show the parameter values. $end
$dumpall
b10 .
b1 -
b0 ,
b1000 +
b1000 $
b1010 #
$end
#0
$dumpvars
b0 3
b0 2
01
b0 0
0/
b0 *
b0 )
b0 (
0'
0&
1%
0"
b0 !
$end
#5000
0%
#10000
1'
1%
#15000
0%
#20000
1%
#25000
0%
#30000
1&
b1 (
b1 )
1%
#35000
0%
#40000
b1 3
1/
b1 0
b10 (
b10 )
1%
#45000
0%
#50000
1"
11
b10 0
b100000001 !
b100000001 *
b100000001 2
b11 (
b11 )
1%
#55000
0%
#60000
b10 !
b10 *
b10 2
b11 0
b100 (
b100 )
1%
#65000
0%
#70000
b100 0
b11 !
b11 *
b11 2
b101 (
b101 )
1%
#75000
0%
#80000
b100 !
b100 *
b100 2
b101 0
b110 (
b110 )
1%
#85000
0%
#90000
b110 0
b101 !
b101 *
b101 2
0&
1%
#95000
0%
#100000
b10 3
b100000110 !
b100000110 *
b100000110 2
0/
1&
b111 (
b111 )
1%
#105000
0%
#110000
0"
01
1/
b111 0
b0 3
b1000 (
b1000 )
1%
#115000
0%
#120000
1"
11
b1000 0
b1001 (
b1001 )
1%
#125000
0%
#130000
b1001 0
b1010 (
b1010 )
1%
#135000
0%
#140000
b1010 0
b1011 (
b1011 )
1%
#145000
0%
#150000
b1011 0
b1100 (
b1100 )
1%
#155000
0%
#160000
b1100 0
0&
1%
#165000
0%
#170000
0/
1%
#175000
0%
#180000
0"
01
1%
